uv_mcp/__init__.py
uv_mcp/actions.py
uv_mcp/diagnostics.py
uv_mcp/errors.py
uv_mcp/models.py
uv_mcp/server.py
uv_mcp/tools.py
uv_mcp/utils.py
uv_mcp_server-0.6.4.dist-info/METADATA
uv_mcp_server-0.6.4.dist-info/WHEEL
uv_mcp_server-0.6.4.dist-info/entry_points.txt
uv_mcp_server-0.6.4.dist-info/licenses/LICENSE
uv_mcp_server-0.6.4.dist-info/RECORD
