Metadata-Version: 2.4
Name: uv-mcp-server
Version: 0.6.4
Summary: Bridge modern, reproducible Python environments with MCP agents. Diagnose, self-heal, and manage uv workflows
Author-email: Saadman Rafat <saadman@outlook.com>
License-File: LICENSE
Requires-Python: >=3.11
Requires-Dist: fastmcp>=0.2.0
Requires-Dist: pydantic>=2.12.5
Requires-Dist: twine>=6.2.0
